djangocms_slider
