Metadata-Version: 1.1
Name: djangocms-slider
Version: 0.2.4
Summary: A slider plugin for djangocms that lets you arrange slides like any other djangocms plugin.
Home-page: https://github.com/urga/djangocms-slider
Author: Urga Creatieve Communicatie
Author-email: dries@urga.be
License: BSD
Keywords: slideshow,django,cms,plugin
Platform: UNKNOWN
Classifier: Development Status :: 3 - Alpha
Classifier: Framework :: Django
Classifier: Framework :: Django :: 1.8
Classifier: Intended Audience :: Developers
Classifier: License :: OSI Approved :: BSD License
Classifier: Natural Language :: English
Classifier: Natural Language :: Dutch
Classifier: Programming Language :: Python :: 2
Classifier: Programming Language :: Python :: 2.7
Classifier: Programming Language :: Python :: 3
Classifier: Programming Language :: Python :: 3.3
Classifier: Programming Language :: Python :: 3.4
Classifier: Programming Language :: Python :: 3.5
